rd60xx/__init__.py
rd60xx/rd60xx.py
rd60xx-0.1.0.dist-info/METADATA
rd60xx-0.1.0.dist-info/WHEEL
rd60xx-0.1.0.dist-info/top_level.txt
rd60xx-0.1.0.dist-info/RECORD
