Metadata-Version: 2.4
Name: rd60xx
Version: 0.1.0
Summary: Helper library for Riden RD60xx programmable power supplies over Modbus RTU (USB)
Author-email: Andrei <andrei.minaev@gmail.com>
License: MIT
Project-URL: Homepage, https://github.com/quantumfish/rd60xx
Requires-Python: >=3.8
Requires-Dist: minimalmodbus
Requires-Dist: pyserial
